pynina/__init__.py
pynina/api_client.py
pynina/const.py
pynina/label_matcher.py
pynina/nina.py
pynina/nina_api.py
pynina/warning.py
pynina/warning_fetcher.py
pynina-1.0.1.dist-info/licenses/LICENSE
pynina-1.0.1.dist-info/METADATA
pynina-1.0.1.dist-info/WHEEL
pynina-1.0.1.dist-info/top_level.txt
pynina-1.0.1.dist-info/RECORD
