Metadata-Version: 2.4
Name: pynina
Version: 1.0.1
Summary: A Python API wrapper to retrieve warnings from the german NINA app.
Author-email: DeerMaximum <git983456@parabelmail.de>
Maintainer-email: DeerMaximum <git983456@parabelmail.de>
License-Expression: MIT
Project-URL: homepage, https://gitlab.com/DeerMaximum/pynina
Project-URL: repository, https://gitlab.com/DeerMaximum/pynina
Keywords: api,wrapper,nina,warning
Classifier: Development Status :: 5 - Production/Stable
Classifier: Framework :: AsyncIO
Classifier: Intended Audience :: Developers
Classifier: Intended Audience :: Information Technology
Classifier: Operating System :: OS Independent
Classifier: Programming Language :: Python
Classifier: Programming Language :: Python :: 3.13
Classifier: Topic :: Internet :: WWW/HTTP
Classifier: Topic :: Software Development
Requires-Python: >=3.13.2
License-File: LICENSE
Requires-Dist: aiohttp~=3.13.3
Dynamic: license-file
